LICENSE.rst
LICENSE_GPL.rst
MANIFEST.in
README.rst
setup.py
src/agx/__init__.py
src/agx.generator.zca.egg-info/PKG-INFO
src/agx.generator.zca.egg-info/SOURCES.txt
src/agx.generator.zca.egg-info/dependency_links.txt
src/agx.generator.zca.egg-info/entry_points.txt
src/agx.generator.zca.egg-info/namespace_packages.txt
src/agx.generator.zca.egg-info/not-zip-safe
src/agx.generator.zca.egg-info/requires.txt
src/agx.generator.zca.egg-info/top_level.txt
src/agx/generator/__init__.py
src/agx/generator/zca/__init__.py
src/agx/generator/zca/configure.zcml
src/agx/generator/zca/generator.rst
src/agx/generator/zca/profiles.py
src/agx/generator/zca/scope.py
src/agx/generator/zca/tests.py
src/agx/generator/zca/utils.py
src/agx/generator/zca/zcagenerator.py
src/agx/generator/zca/profiles/zca.profile.di
src/agx/generator/zca/profiles/zca.profile.notation
src/agx/generator/zca/profiles/zca.profile.uml
src/agx/generator/zca/testing/__init__.py
src/agx/generator/zca/testing/data/agx.generator.zca-sample.di
src/agx/generator/zca/testing/data/agx.generator.zca-sample.notation
src/agx/generator/zca/testing/data/agx.generator.zca-sample.uml
src/agx/generator/zca/testing/data/agx.generator.zca-sample/LICENSE.rst
src/agx/generator/zca/testing/data/agx.generator.zca-sample/MANIFEST.rst
src/agx/generator/zca/testing/data/agx.generator.zca-sample/README.rst
src/agx/generator/zca/testing/data/agx.generator.zca-sample/setup.py
src/agx/generator/zca/testing/data/agx.generator.zca-sample/src/agx/__init__.py
src/agx/generator/zca/testing/data/agx.generator.zca-sample/src/agx/testpackage/__init__.py
src/agx/generator/zca/testing/data/agx.generator.zca-sample/src/agx/testpackage/adapters.py
src/agx/generator/zca/testing/data/agx.generator.zca-sample/src/agx/testpackage/adapters.zcml
src/agx/generator/zca/testing/data/agx.generator.zca-sample/src/agx/testpackage/common.py
src/agx/generator/zca/testing/data/agx.generator.zca-sample/src/agx/testpackage/configure.zcml
src/agx/generator/zca/testing/data/agx.generator.zca-sample/src/agx/testpackage/interfaces.py
src/agx/generator/zca/testing/data/agx.generator.zca-sample/src/agx/testpackage/subscribers.py
src/agx/generator/zca/testing/data/agx.generator.zca-sample/src/agx/testpackage/subscribers.zcml
src/agx/generator/zca/testing/data/agx.generator.zca-sample/src/agx/testpackage/utilities.py