Metadata-Version: 1.1
Name: agx.generator.zca
Version: 1.0a1
Summary: AGX generator for zope component architecture
Home-page: http://github.com/bluedynamics/agx.generator.zca
Author: BlueDynamics Alliance
Author-email: dev@bluedynamics.com
License: GNU General Public Licence
Keywords: AGX,Code Generator
Platform: UNKNOWN
Classifier: Development Status :: 3 - Alpha
Classifier: License :: OSI Approved :: GNU General Public License (GPL)
Classifier: Programming Language :: Python
